deepmocca/__init__.py
deepmocca/main.py
deepmocca-1.0.0.dist-info/LICENSE
deepmocca-1.0.0.dist-info/METADATA
deepmocca-1.0.0.dist-info/WHEEL
deepmocca-1.0.0.dist-info/entry_points.txt
deepmocca-1.0.0.dist-info/top_level.txt
deepmocca-1.0.0.dist-info/zip-safe
deepmocca-1.0.0.dist-info/RECORD
