Metadata-Version: 2.1
Name: deepmocca
Version: 1.0.0
Summary: DeepMOCCA
Home-page: UNKNOWN
Author: Sara Althubaiti
Author-email: sara.althubaiti@kaust.edu.sa
License: Apache 2.0
Download-URL: https://github.com/bio-ontology-research-group/deepmocca/archive/v1.0.0.tar.gz
Platform: UNKNOWN
Requires-Python: <3.8
Requires-Dist: torch (<1.8)
Requires-Dist: click (<8)
Requires-Dist: pandas (<2)
Requires-Dist: numpy
Requires-Dist: scipy
Requires-Dist: torch-scatter
Requires-Dist: torch-sparse
Requires-Dist: torch-cluster
Requires-Dist: torch-spline-conv
Requires-Dist: torch-geometric
